xpipe_api/__init__.py
xpipe_api/clients.py
xpipe_api/exceptions.py
xpipe_api-0.1.31.dist-info/LICENSE
xpipe_api-0.1.31.dist-info/METADATA
xpipe_api-0.1.31.dist-info/WHEEL
xpipe_api-0.1.31.dist-info/RECORD
