Metadata-Version: 2.3
Name: xpipe_api
Version: 0.1.31
Summary: Client for the XPipe API
License: MIT
Author: Clint Olson
Author-email: coandco@gmail.com
Requires-Python: >=3.10,<4.0
Classifier: License :: OSI Approved :: MIT License
Classifier: Programming Language :: Python :: 3
Classifier: Programming Language :: Python :: 3.10
Classifier: Programming Language :: Python :: 3.11
Classifier: Programming Language :: Python :: 3.12
Classifier: Programming Language :: Python :: 3.13
Requires-Dist: aiohttp-requests (>=0.2.4,<0.3.0)
Requires-Dist: packaging (>=24.1,<25.0)
Requires-Dist: requests (>=2.32.3,<3.0.0)
Project-URL: Repository, https://github.com/xpipe-io/xpipe-python-api
